{
  "kind": "collectionType",
  "collectionName": "elevate_categories",
  "info": {
    "singularName": "elevate-category",
    "pluralName": "elevate-categories",
    "displayName": "ElevateCategory",
    "description": ""
  },
  "options": {
    "draftAndPublish": true
  },
  "pluginOptions": {},
  "attributes": {
    "title": {
      "type": "string"
    },
    "displayTitle": {
      "type": "string"
    },
    "description": {
      "type": "string"
    },
    "queryIdentifier": {
      "type": "string",
      "unique": true
    }
  }
}
